pytest_timeouts.py
pytest_timeouts-1.0.0.dist-info/METADATA
pytest_timeouts-1.0.0.dist-info/RECORD
pytest_timeouts-1.0.0.dist-info/WHEEL
pytest_timeouts-1.0.0.dist-info/entry_points.txt
pytest_timeouts-1.0.0.dist-info/top_level.txt
