Metadata-Version: 2.1
Name: pytest-timeouts
Version: 1.0.0
Summary: Linux-only Pytest plugin to control durations of various test case execution phases
Home-page: https://github.com/Scony/pytest-timeouts
Author: Pawel Lampe
Author-email: pawel.lampe@gmail.com
License: MIT
Platform: UNKNOWN
Requires-Dist: pytest
